exponential/__init__.py
exponential/main.py
developer_tools_exponential-0.1.1.dist-info/LICENSE
developer_tools_exponential-0.1.1.dist-info/METADATA
developer_tools_exponential-0.1.1.dist-info/WHEEL
developer_tools_exponential-0.1.1.dist-info/top_level.txt
developer_tools_exponential-0.1.1.dist-info/RECORD
