Metadata-Version: 2.1
Name: developer-tools-exponential
Version: 0.1.1
Summary: Flask module for request validation
Author: Exponential
Author-email: dev@exponentialhost.com
Classifier: Programming Language :: Python :: 3
Classifier: License :: OSI Approved :: MIT License
Classifier: Operating System :: OS Independent
Requires-Python: >=3.6
License-File: LICENSE
Requires-Dist: Flask
